{
  "project_info": {
    "project_number": "1003591168260",
    "firebase_url": "https://beautipackapp.firebaseio.com",
    "project_id": "beautipackapp",
    "storage_bucket": "beautipackapp.appspot.com"
  },
  "client": [
    {
      "client_info": {
        "mobilesdk_app_id": "1:1003591168260:android:6a286988d9010bf2916051",
        "android_client_info": {
          "package_name": "com.example.beautipackapp"
        }
      },
      "oauth_client": [
        {
          "client_id": "1003591168260-49af6suhmh79fihdkofmnr3iba981ljl.apps.googleusercontent.com",
          "client_type": 3
        }
      ],
      "api_key": [
        {
          "current_key": "AIzaSyAQKshuBscISSkoUZTapXnlM0OSgwivRqk"
        }
      ],
      "services": {
        "appinvite_service": {
          "other_platform_oauth_client": [
            {
              "client_id": "1003591168260-49af6suhmh79fihdkofmnr3iba981ljl.apps.googleusercontent.com",
              "client_type": 3
            }
          ]
        }
      }
    }
  ],
  "configuration_version": "1"
}